fastgemf/GEMFcore.py
fastgemf/GEMFsimulation.py
fastgemf/__init__.py
fastgemf/error.py
fastgemf/initial_condition.py
fastgemf/initializer.py
fastgemf/modelconfiguration.py
fastgemf/modelschema.py
fastgemf/network.py
fastgemf/post_population.py
fastgemf/stop_conditions.py
fastgemf/times_structure.py
fastgemf/utils.py
fastgemf/visualization.py
fastgemf-0.1.4.dist-info/METADATA
fastgemf-0.1.4.dist-info/WHEEL
fastgemf-0.1.4.dist-info/top_level.txt
fastgemf-0.1.4.dist-info/RECORD
