Metadata-Version: 2.4
Name: fastgemf
Version: 0.1.4
Summary: Scalable High-Speed Simulation of Stochastic Spreading Processes over Complex Multilayer Networks
Author-email: Mohammad Hossein Samaei <m.hosseinsamaei@gmail.com>
License: MIT
Project-URL: Homepage, https://github.com/KSUNetSE/FastGEMF
Project-URL: Repository, https://github.com/KSUNetSE/FastGEMF
Project-URL: Documentation, https://github.com/KSUNetSE/FastGEMF#readme
Keywords: epidemic,simulation,network,stochastic,multilayer
Classifier: Programming Language :: Python :: 3
Classifier: License :: OSI Approved :: MIT License
Classifier: Operating System :: OS Independent
Requires-Python: >=3.9
Requires-Dist: numpy
Requires-Dist: pandas
Requires-Dist: pyyaml
Requires-Dist: networkx
Requires-Dist: matplotlib
Requires-Dist: tqdm
Requires-Dist: scipy
Requires-Dist: sortedcontainers
Requires-Dist: pyvis
